laughingface/__init__.py
laughingface/core.py
laughingface-0.1.4.dist-info/licenses/LICENSE
laughingface-0.1.4.dist-info/METADATA
laughingface-0.1.4.dist-info/WHEEL
laughingface-0.1.4.dist-info/top_level.txt
laughingface-0.1.4.dist-info/RECORD
